pygendata/__init__.py
pygendata/datatypes.py
pygendata/ddl.py
pygendata/exceptions.py
pygendata/cli/__init__.py
pygendata/managers/__init__.py
pygendata/managers/csvmanager.py
pygendata/managers/jsonmanager.py
pygendata/managers/tsvmanager.py
pygendata/templates/__init__.py
pygendata/templates/geo.py
tests/__init__.py
tests/test_data_generator.py
pygendata-1.0.6.dist-info/LICENSE.txt
pygendata-1.0.6.dist-info/METADATA
pygendata-1.0.6.dist-info/WHEEL
pygendata-1.0.6.dist-info/entry_points.txt
pygendata-1.0.6.dist-info/top_level.txt
pygendata-1.0.6.dist-info/RECORD
